grenaultgetscode/__init__.py
grenaultgetscode/script.py
grenaultgetscode-0.1.0.dist-info/entry_points.txt
grenaultgetscode-0.1.0.dist-info/WHEEL
grenaultgetscode-0.1.0.dist-info/METADATA
grenaultgetscode-0.1.0.dist-info/RECORD
